{
	"credit": "Made with Blockbench",
	"texture_size": [128, 128],
	"textures": {
		"0": "achievetodo:item/iron_golem/iron_golem",
		"particle": "achievetodo:item/iron_golem/iron_golem"
	},
	"elements": [
		{
			"from": [4, 4, 6.5],
			"to": [12, 14, 7.5],
			"faces": {
				"east": {"uv": [2, 1, 2.125, 2.25], "texture": "#0"},
				"south": {"uv": [1, 1, 2, 2.25], "texture": "#0"},
				"west": {"uv": [0.875, 1, 1, 2.25], "texture": "#0"},
				"up": {"uv": [1, 0.875, 2, 1], "texture": "#0"},
				"down": {"uv": [2, 0.875, 3, 1], "texture": "#0"}
			}
		},
		{
			"from": [7, 3, 7.75],
			"to": [9, 7, 9.75],
			"faces": {
				"east": {"uv": [3.5, 0.25, 3.75, 0.75], "texture": "#0"},
				"south": {"uv": [3.25, 0.25, 3.5, 0.75], "texture": "#0"},
				"west": {"uv": [3, 0.25, 3.25, 0.75], "texture": "#0"},
				"up": {"uv": [3.25, 0, 3.5, 0.25], "texture": "#0"},
				"down": {"uv": [3.5, 0, 3.75, 0.25], "texture": "#0"}
			}
		}
	]
}